pytestshot_compare
pytestshot
