Metadata-Version: 1.1
Name: pytestshot
Version: 0.2
Summary: Automated tests for Python/GTK using screenshots and image processing
Home-page: https://github.com/jflesch/pytestshot#readme
Author: Jerome Flesch
Author-email: jflesch@gmail.com
License: GPLv3+
Download-URL: https://github.com/jflesch/pytestshot/archive/master.tar.gz
Keywords: tests
Platform: UNKNOWN
Classifier: Development Status :: 5 - Production/Stable
Classifier: Intended Audience :: End Users/Desktop
Classifier: License :: OSI Approved :: GNU General Public License v3 or later (GPLv3+)
Classifier: Operating System :: POSIX :: Linux
Classifier: Programming Language :: Python :: 3
Classifier: Topic :: Multimedia :: Graphics :: Graphics Conversion
Classifier: Topic :: Scientific/Engineering :: Image Recognition
